erepublik_api/__init__.py
erepublik_api/client.py
erepublik_api-0.1.1.dist-info/licenses/LICENSE
erepublik_api-0.1.1.dist-info/METADATA
erepublik_api-0.1.1.dist-info/WHEEL
erepublik_api-0.1.1.dist-info/top_level.txt
erepublik_api-0.1.1.dist-info/RECORD
