Metadata-Version: 2.4
Name: erepublik-api
Version: 0.1.1
Summary: Python wrapper for the eRepublik API
Author-email: Curlybear <me@curlybear.eu>
License: MIT
Project-URL: Homepage, https://github.com/curlybear/erepublik-api
Requires-Python: >=3.6
License-File: LICENSE
Requires-Dist: requests
Dynamic: license-file
